dbload/__init__.py
dbload/cli.py
dbload/config.py
dbload/config_singleton.py
dbload/connection.py
dbload/context.py
dbload/context_singleton.py
dbload/exceptions.py
dbload/query.py
dbload/query_parser.py
dbload/query_result.py
dbload/resources/__init__.py
dbload/resources/ibm-db2.sql
dbload/resources/ms-sql.sql
dbload/resources/sap-hana.sql
dbload/resources/scenarios.py
dbload/resources/sqlite.sql
dbload/scenario.py
dbload/tests/__init__.py
dbload/tests/conftest.py
dbload/tests/context/__init__.py
dbload/tests/debug.py
dbload/tests/parser/__init__.py
dbload/tests/parser/test_invocation.py
dbload/tests/query/__init__.py
dbload/tests/query/test_cursor_validation.py
dbload/tests/query/test_initialization.py
dbload/tests/query/test_invocation.py
dbload/tests/return_random/__init__.py
dbload/tests/return_random/test_initialization.py
dbload/tests/return_random/test_invocation.py
dbload/tests/scenario/__init__.py
dbload/tests/scenario/test_initialization.py
dbload/tests/scenario/test_invocation.py
db_load_generator-0.8.6.dist-info/entry_points.txt
db_load_generator-0.8.6.dist-info/LICENSE
db_load_generator-0.8.6.dist-info/WHEEL
db_load_generator-0.8.6.dist-info/METADATA
db_load_generator-0.8.6.dist-info/RECORD
