Metadata-Version: 2.1
Name: db-load-generator
Version: 0.8.6
Summary: Database load generator.
Home-page: https://github.com/dynatrace-oss/db-load-generator
License: Apache-2.0
Keywords: database,load,bench,generator
Author: Vagiz Duseev
Author-email: vagiz.duseev@dynatrace.com
Maintainer: Vagiz Duseev
Maintainer-email: vagiz.duseev@dynatrace.com
Requires-Python: >=3.9,<4.0
Classifier: License :: OSI Approved :: Apache Software License
Classifier: Programming Language :: Python :: 3
Classifier: Programming Language :: Python :: 3.9
Provides-Extra: dramatiq
Requires-Dist: APScheduler (>=3.7.0,<4.0.0); extra == "dramatiq"
Requires-Dist: Faker (>=8.1.2,<9.0.0)
Requires-Dist: JPype1 (>=1.2.0,<2.0.0)
Requires-Dist: click (>=7.1.2,<8.0.0)
Requires-Dist: dramatiq[rabbitmq] (>=1.11.0,<2.0.0); extra == "dramatiq"
Requires-Dist: ilexconf (>=0.9.6,<0.10.0)
Requires-Dist: loguru (>=0.5.3,<0.6.0)
Requires-Dist: mapz (>=1.1.28,<2.0.0)
Requires-Dist: prettytable (>=2.1.0,<3.0.0)
Project-URL: Documentation, https://db-load-generator.readthedocs.io
Project-URL: Repository, https://github.com/dynatrace-oss/db-load-generator
